gateagent/__init__.py
gateagent/client.py
gateagent/schemas.py
gateagent/tracer.py
gateagent-0.1.9.dist-info/METADATA
gateagent-0.1.9.dist-info/WHEEL
gateagent-0.1.9.dist-info/top_level.txt
gateagent-0.1.9.dist-info/RECORD
