Metadata-Version: 2.4
Name: gateagent
Version: 0.1.9
Summary: Get insights on your agent and app interations.
Author: Gateagent
Author-email: Anshul Basia <anshulbasia@alumni.iitd.ac.in>, Siddharth Goyal <goyal.siddharth22@gmail.com>
Maintainer-email: Anshul Basia <anshulbasia@alumni.iitd.ac.in>, Siddharth Goyal <goyal.siddharth22@gmail.com>
License-Expression: MIT
Keywords: agent,gateway,tracking,events,fastapi,ai
Classifier: Development Status :: 3 - Alpha
Classifier: Intended Audience :: Developers
Classifier: Programming Language :: Python :: 3
Classifier: Programming Language :: Python :: 3.10
Classifier: Programming Language :: Python :: 3.11
Classifier: Programming Language :: Python :: 3.12
Classifier: Framework :: FastAPI
Classifier: Topic :: Software Development :: Libraries :: Python Modules
Requires-Python: >=3.9
Requires-Dist: langchain-core
Requires-Dist: pydantic>=2.0.0
Requires-Dist: requests
Provides-Extra: dev
Dynamic: author
Dynamic: requires-python
